{
    "idSave": 719,
    "isFirstSession": false,
    "language": "ru",
    "promptDone": false,
    "money": 1,
    "newPlayerName": "Hello!",
    "openLevels": [
        false,
        true,
        false
    ],
    "Money": 97095,
    "EngineLevel": 25,
    "EngineSpeed": 7.799996376037598,
    "MagnetLevel": 1,
    "CargoLevel": 1,
    "PriceUpgradeEngine": 325.0413513183594,
    "PriceUpgradeMagnet": 30.0,
    "PriceUpgradeCargo": 30.0,
    "IsRustForkActive": true,
    "IsSilverForkActive": false,
    "IsGoldForkActive": false,
    "IsLowWheelsActive": false,
    "IsMiddleWheelsActive": false,
    "IsHighWheelsActive": true
}