{
    "idSave": 8642,
    "isFirstSession": false,
    "language": "ru",
    "promptDone": false,
    "money": 1,
    "newPlayerName": "Hello!",
    "openLevels": [
        false,
        true,
        false
    ],
    "Money": 0,
    "EngineLevel": 1,
    "EngineSpeed": 3.0,
    "MagnetLevel": 1,
    "CargoLevel": 1,
    "PriceUpgradeEngine": 30.0,
    "PriceUpgradeMagnet": 30.0,
    "PriceUpgradeCargo": 30.0,
    "IsRustForkActive": true,
    "IsSilverForkActive": false,
    "IsGoldForkActive": false,
    "IsLowWheelsActive": true,
    "IsMiddleWheelsActive": false,
    "IsHighWheelsActive": false,
    "IsLowMagnegActive": true,
    "IslowMagnetHighChainActive": false,
    "IsMiddleMagnetActive": false,
    "IsMiddleMagnetHighChainActive": false,
    "IsHighMagnetActive": false,
    "IsHighMagnetLowChainActive": false,
    "IsBarrierJailActive": true,
    "IsBarrierForgeActive": true,
    "IsBarrierThroneActive": true
}